mcp_powershell/__init__.py
powershell_mcp-1.0.5.dist-info/METADATA
powershell_mcp-1.0.5.dist-info/WHEEL
powershell_mcp-1.0.5.dist-info/entry_points.txt
powershell_mcp-1.0.5.dist-info/top_level.txt
powershell_mcp-1.0.5.dist-info/RECORD
